README.md
setup.py
eschool/__init__.py
eschool/eschool.py
eschool/eschool_base.py
eschool.egg-info/PKG-INFO
eschool.egg-info/SOURCES.txt
eschool.egg-info/dependency_links.txt
eschool.egg-info/requires.txt
eschool.egg-info/top_level.txt