Metadata-Version: 1.0
Name: eschool
Version: 1.2.11
Summary: Python library to work with Eschool electronic diary
Home-page: https://github.com/ennucore/eschool_py
Author: ennucore
Author-email: UNKNOWN
License: MIT
Platform: UNKNOWN
